firebird/driver/__init__.py
firebird/driver/config.py
firebird/driver/core.py
firebird/driver/fbapi.py
firebird/driver/hooks.py
firebird/driver/interfaces.py
firebird/driver/types.py
firebird_driver-2.0.1.dist-info/METADATA
firebird_driver-2.0.1.dist-info/WHEEL
firebird_driver-2.0.1.dist-info/licenses/LICENSE
firebird_driver-2.0.1.dist-info/RECORD
